frdate/__init__.py
frdate-2.0.0.dist-info/LICENSE
frdate-2.0.0.dist-info/METADATA
frdate-2.0.0.dist-info/WHEEL
frdate-2.0.0.dist-info/top_level.txt
frdate-2.0.0.dist-info/RECORD
