Metadata-Version: 2.1
Name: frdate
Version: 2.0.0
Summary: Converts french text to python date object
Author-email: Thibaut_S <py@spriet.online>
License: MIT-License
Project-URL: Homepage, https://gitlab.com/Thibaut_S/frdate
Project-URL: Bug Tracker, https://gitlab.com/Thibaut_S/frdate/-/issues
Keywords: dates,french,français,conversion
Classifier: Programming Language :: Python :: 3
Requires-Python: >=3.8
License-File: LICENSE
Requires-Dist: wheel
Requires-Dist: dateutils
Requires-Dist: euros
Requires-Dist: pytest
Requires-Dist: ruff
Requires-Dist: black
Requires-Dist: pip-tools
